{
  "documentName": "[Edit: it's me]*",
  "exportedAtUtc": "2026-02-11T05:30:03.9742599Z",
  "nodes": [
    {
      "id": "2e5929ab-1284-4c01-9910-62584152ca27",
      "inputs": [],
      "name": "Layer",
      "outputs": [],
      "type": "Grasshopper.Rhinoceros.Model.Params.Param_ModelLayer"
    },
    {
      "id": "31c3c1c1-8fb7-4c66-a4fa-09a2e6bf88f5",
      "inputs": [],
      "name": "Button",
      "outputs": [],
      "type": "Grasshopper.Kernel.Special.GH_ButtonObject"
    },
    {
      "id": "341b765c-2c53-4edc-9fcd-0da355dd6594",
      "inputs": [],
      "name": "Button",
      "outputs": [],
      "type": "Grasshopper.Kernel.Special.GH_ButtonObject"
    },
    {
      "id": "342a76f3-c36b-450c-af4a-c4a933473d17",
      "inputs": [],
      "name": "Hatch Pattern",
      "outputs": [],
      "type": "Grasshopper.Rhinoceros.Drafting.Params.Param_ModelHatchPattern"
    },
    {
      "id": "356a9e19-bc5e-4ddf-a193-74660a941235",
      "inputs": [],
      "name": "Panel",
      "outputs": [],
      "type": "Grasshopper.Kernel.Special.GH_Panel"
    },
    {
      "id": "38eca5d5-7db1-4fb9-99e3-4dfe56692534",
      "inputs": [],
      "name": "Panel",
      "outputs": [],
      "type": "Grasshopper.Kernel.Special.GH_Panel"
    },
    {
      "id": "395f192c-c268-4023-a5ab-f6b2c9a0fc78",
      "inputs": [],
      "name": "Toggle",
      "outputs": [],
      "type": "Grasshopper.Kernel.Special.GH_BooleanToggle"
    },
    {
      "id": "5518c220-8eed-4aa0-a4e5-cc92b8371493",
      "inputs": [],
      "name": "Toggle",
      "outputs": [],
      "type": "Grasshopper.Kernel.Special.GH_BooleanToggle"
    },
    {
      "id": "5c3287f9-a965-45d9-86ec-55439a25391b",
      "inputs": [],
      "name": "B",
      "outputs": [],
      "type": "Grasshopper.Kernel.Special.GH_ClusterOutputHook"
    },
    {
      "id": "60da20d1-f1ef-450d-88f0-9e766bb2ad38",
      "inputs": [],
      "name": "Panel",
      "outputs": [],
      "type": "Grasshopper.Kernel.Special.GH_Panel"
    },
    {
      "id": "6d119461-bb08-4db9-92d8-10d3f1d01b69",
      "inputs": [
        {
          "access": "item",
          "name": "Run",
          "nickname": "Run",
          "type": "Generic Data"
        },
        {
          "access": "item",
          "name": "RepoPath",
          "nickname": "RepoPath",
          "type": "Generic Data"
        },
        {
          "access": "item",
          "name": "JsonRelPath",
          "nickname": "JsonRelPath",
          "type": "Generic Data"
        },
        {
          "access": "item",
          "name": "Select",
          "nickname": "Select",
          "type": "Generic Data"
        },
        {
          "access": "item",
          "name": "Badges",
          "nickname": "Badges",
          "type": "Generic Data"
        },
        {
          "access": "item",
          "name": "ClearSelection",
          "nickname": "ClearSelection",
          "type": "Generic Data"
        }
      ],
      "name": "Py3",
      "outputs": [
        {
          "access": "item",
          "name": "out",
          "nickname": "out",
          "type": "Text"
        },
        {
          "access": "item",
          "name": "Summary",
          "nickname": "Summary",
          "type": "Generic Data"
        },
        {
          "access": "item",
          "name": "ChangedIds",
          "nickname": "ChangedIds",
          "type": "Generic Data"
        }
      ],
      "type": "RhinoCodePluginGH.Components.Python3Component"
    },
    {
      "id": "8b4f993b-fc4b-4c11-acf4-cc5ee8db48fc",
      "inputs": [],
      "name": "Box",
      "outputs": [],
      "type": "Grasshopper.Kernel.Parameters.Param_Box"
    },
    {
      "id": "ac0c048d-77a8-4066-97d4-c426eeac00d1",
      "inputs": [],
      "name": "Number Slider",
      "outputs": [],
      "type": "Grasshopper.Kernel.Special.GH_NumberSlider"
    },
    {
      "id": "ae7d654f-a046-47c9-997f-5b7a4775a348",
      "inputs": [
        {
          "access": "item",
          "name": "Export",
          "nickname": "Export",
          "type": "Generic Data"
        },
        {
          "access": "item",
          "name": "Path",
          "nickname": "Path",
          "type": "Generic Data"
        }
      ],
      "name": "Py3",
      "outputs": [
        {
          "access": "item",
          "name": "out",
          "nickname": "out",
          "type": "Text"
        },
        {
          "access": "item",
          "name": "Json",
          "nickname": "Json",
          "type": "Generic Data"
        }
      ],
      "type": "RhinoCodePluginGH.Components.Python3Component"
    },
    {
      "id": "b0969f90-303d-46ce-a73f-8e81738e98e9",
      "inputs": [
        {
          "access": "item",
          "name": "A",
          "nickname": "A",
          "type": "Generic Data"
        },
        {
          "access": "item",
          "name": "B",
          "nickname": "B",
          "type": "Generic Data"
        }
      ],
      "name": "A\u00d7B",
      "outputs": [
        {
          "access": "item",
          "name": "Result",
          "nickname": "R",
          "type": "Generic Data"
        }
      ],
      "type": "MathComponents.OperatorComponents.Component_VariableMultiplication"
    },
    {
      "id": "b10c64d0-bc01-4398-844d-54cebd6b782c",
      "inputs": [],
      "name": "B",
      "outputs": [],
      "type": "Grasshopper.Kernel.Special.GH_ClusterInputHook"
    },
    {
      "id": "c7779a3d-89be-4dd4-b705-89a285575045",
      "inputs": [],
      "name": "Mesh",
      "outputs": [],
      "type": "Grasshopper.Kernel.Parameters.Param_Mesh"
    },
    {
      "id": "d9b97e17-697a-477d-b7ef-43376708b57a",
      "inputs": [],
      "name": "Crv",
      "outputs": [],
      "type": "Grasshopper.Kernel.Parameters.Param_Curve"
    },
    {
      "id": "dc62be4f-b71f-47c6-8792-a0f6c7a0718f",
      "inputs": [],
      "name": "Panel",
      "outputs": [],
      "type": "Grasshopper.Kernel.Special.GH_Panel"
    },
    {
      "id": "e0aea22c-fc5c-46a2-8c42-a067f21406f8",
      "inputs": [],
      "name": "Panel",
      "outputs": [],
      "type": "Grasshopper.Kernel.Special.GH_Panel"
    },
    {
      "id": "e857fa1a-3ec8-494b-8e54-ebcc9c4ea8d3",
      "inputs": [
        {
          "access": "item",
          "name": "Base",
          "nickname": "B",
          "type": "Plane"
        },
        {
          "access": "item",
          "name": "X",
          "nickname": "X",
          "type": "Number"
        },
        {
          "access": "item",
          "name": "Y",
          "nickname": "Y",
          "type": "Number"
        },
        {
          "access": "item",
          "name": "Z",
          "nickname": "Z",
          "type": "Number"
        }
      ],
      "name": "Box",
      "outputs": [
        {
          "access": "item",
          "name": "Box",
          "nickname": "B",
          "type": "Box"
        }
      ],
      "type": "SurfaceComponents.PrimitiveComponents.Component_CenterBox"
    }
  ],
  "schema": "gh-cluster-graph-v1",
  "wires": [
    {
      "fromIndex": 0,
      "fromNode": "24cbb091-bf81-41a9-8319-f90cd6bd07df",
      "toIndex": 1,
      "toNode": "e857fa1a-3ec8-494b-8e54-ebcc9c4ea8d3"
    },
    {
      "fromIndex": 0,
      "fromNode": "24cbb091-bf81-41a9-8319-f90cd6bd07df",
      "toIndex": 2,
      "toNode": "e857fa1a-3ec8-494b-8e54-ebcc9c4ea8d3"
    },
    {
      "fromIndex": 0,
      "fromNode": "24cbb091-bf81-41a9-8319-f90cd6bd07df",
      "toIndex": 3,
      "toNode": "e857fa1a-3ec8-494b-8e54-ebcc9c4ea8d3"
    },
    {
      "fromIndex": 0,
      "fromNode": "31c3c1c1-8fb7-4c66-a4fa-09a2e6bf88f5",
      "toIndex": 0,
      "toNode": "ae7d654f-a046-47c9-997f-5b7a4775a348"
    },
    {
      "fromIndex": 0,
      "fromNode": "341b765c-2c53-4edc-9fcd-0da355dd6594",
      "toIndex": 0,
      "toNode": "6d119461-bb08-4db9-92d8-10d3f1d01b69"
    },
    {
      "fromIndex": 0,
      "fromNode": "38eca5d5-7db1-4fb9-99e3-4dfe56692534",
      "toIndex": 1,
      "toNode": "ae7d654f-a046-47c9-997f-5b7a4775a348"
    },
    {
      "fromIndex": 0,
      "fromNode": "395f192c-c268-4023-a5ab-f6b2c9a0fc78",
      "toIndex": 3,
      "toNode": "6d119461-bb08-4db9-92d8-10d3f1d01b69"
    },
    {
      "fromIndex": 0,
      "fromNode": "5518c220-8eed-4aa0-a4e5-cc92b8371493",
      "toIndex": 4,
      "toNode": "6d119461-bb08-4db9-92d8-10d3f1d01b69"
    },
    {
      "fromIndex": 0,
      "fromNode": "60da20d1-f1ef-450d-88f0-9e766bb2ad38",
      "toIndex": 1,
      "toNode": "6d119461-bb08-4db9-92d8-10d3f1d01b69"
    },
    {
      "fromIndex": 0,
      "fromNode": "b10c64d0-bc01-4398-844d-54cebd6b782c",
      "toIndex": 1,
      "toNode": "b0969f90-303d-46ce-a73f-8e81738e98e9"
    },
    {
      "fromIndex": 0,
      "fromNode": "dc62be4f-b71f-47c6-8792-a0f6c7a0718f",
      "toIndex": 2,
      "toNode": "6d119461-bb08-4db9-92d8-10d3f1d01b69"
    }
  ]
}